<?xml version='1.0' encoding='UTF-8'?>
<md:EntityDescriptor xmlns:md="urn:oasis:names:tc:SAML:2.0:metadata" xmlns:alg="urn:oasis:names:tc:SAML:metadata:algsupport" xmlns:ds="http://www.w3.org/2000/09/xmldsig#" xmlns:eidas="http://eidas.europa.eu/saml-extensions" xmlns:idpdisc="urn:oasis:names:tc:SAML:profiles:SSO:idp-discovery-protocol" xmlns:init="urn:oasis:names:tc:SAML:profiles:SSO:request-init" xmlns:mdattr="urn:oasis:names:tc:SAML:metadata:attribute" xmlns:mdrpi="urn:oasis:names:tc:SAML:metadata:rpi" xmlns:mdui="urn:oasis:names:tc:SAML:metadata:ui" xmlns:pyff="http://pyff.io/NS" xmlns:saml="urn:oasis:names:tc:SAML:2.0:assertion" xmlns:ser="http://eidas.europa.eu/metadata/servicelist" xmlns:shibmd="urn:mace:shibboleth:metadata:1.0" xmlns:xenc="http://www.w3.org/2001/04/xmlenc#" xmlns:xrd="http://docs.oasis-open.org/ns/xri/xrd-1.0" xmlns:xs="http://www.w3.org/2001/XMLSchema" xmlns:xsi="http://www.w3.org/2001/XMLSchema-instance" xmlns="urn:oasis:names:tc:SAML:2.0:metadata" entityID="https://sp.onlinelibrary.wiley.com/shibboleth">
	<md:Extensions>
	<alg:DigestMethod Algorithm="http://www.w3.org/2001/04/xmlenc#sha512"/>
	<alg:DigestMethod Algorithm="http://www.w3.org/2001/04/xmldsig-more#sha384"/>
	<alg:DigestMethod Algorithm="http://www.w3.org/2001/04/xmlenc#sha256"/>
	<alg:DigestMethod Algorithm="http://www.w3.org/2001/04/xmldsig-more#sha224"/>
	<alg:DigestMethod Algorithm="http://www.w3.org/2000/09/xmldsig#sha1"/>
	<alg:SigningMethod Algorithm="http://www.w3.org/2001/04/xmldsig-more#ecdsa-sha512"/>
	<alg:SigningMethod Algorithm="http://www.w3.org/2001/04/xmldsig-more#ecdsa-sha384"/>
	<alg:SigningMethod Algorithm="http://www.w3.org/2001/04/xmldsig-more#ecdsa-sha256"/>
	<alg:SigningMethod Algorithm="http://www.w3.org/2001/04/xmldsig-more#ecdsa-sha224"/>
	<alg:SigningMethod Algorithm="http://www.w3.org/2001/04/xmldsig-more#rsa-sha512"/>
	<alg:SigningMethod Algorithm="http://www.w3.org/2001/04/xmldsig-more#rsa-sha384"/>
	<alg:SigningMethod Algorithm="http://www.w3.org/2001/04/xmldsig-more#rsa-sha256"/>
	<alg:SigningMethod Algorithm="http://www.w3.org/2009/xmldsig11#dsa-sha256"/>
	<alg:SigningMethod Algorithm="http://www.w3.org/2001/04/xmldsig-more#ecdsa-sha1"/>
	<alg:SigningMethod Algorithm="http://www.w3.org/2000/09/xmldsig#rsa-sha1"/>
	<alg:SigningMethod Algorithm="http://www.w3.org/2000/09/xmldsig#dsa-sha1"/>
	<mdrpi:RegistrationInfo registrationAuthority="http://ukfederation.org.uk" registrationInstant="2010-07-27T11:15:10Z">
		<mdrpi:RegistrationPolicy xml:lang="en">http://ukfederation.org.uk/doc/mdrps-20130902</mdrpi:RegistrationPolicy>
	</mdrpi:RegistrationInfo>
	</md:Extensions>
	<md:SPSSODescriptor protocolSupportEnumeration="urn:oasis:names:tc:SAML:2.0:protocol urn:oasis:names:tc:SAML:1.1:protocol urn:oasis:names:tc:SAML:1.0:protocol">
	<md:Extensions>
		<mdui:UIInfo>
		<mdui:DisplayName xml:lang="en">John Wiley &amp; Sons Limited: Wiley Online Library</mdui:DisplayName>
		<mdui:Description xml:lang="en">This service allows Wiley Online Library users to use login credentials at their home organisations</mdui:Description>
		<mdui:Logo height="60" width="74">https://sp.onlinelibrary.wiley.com/images/WOL_Stacked_k.gif</mdui:Logo>
		<mdui:Logo height="16" width="16">https://sp.onlinelibrary.wiley.com/images/WOL_favicon.png</mdui:Logo>
		</mdui:UIInfo>
		<init:RequestInitiator Binding="urn:oasis:names:tc:SAML:profiles:SSO:request-init" Location="https://sp.onlinelibrary.wiley.com/Shibboleth.sso/DS"/>
		<idpdisc:DiscoveryResponse Binding="urn:oasis:names:tc:SAML:profiles:SSO:idp-discovery-protocol" Location="https://sp.onlinelibrary.wiley.com/Shibboleth.sso/DS" index="1"/>
	</md:Extensions>
	<md:KeyDescriptor>
		<ds:KeyInfo>
		<ds:X509Data>
			<ds:X509Certificate>
MIIDqjCCApICCQCHTdBLBp/WwDANBgkqhkiG9w0BAQUFADCBljELMAkGA1UEBhMC
VVMxEzARBgNVBAgMCk5ldyBKZXJzZXkxETAPBgNVBAcMCFNvbWVyc2V0MR8wHQYD
VQQKDBZKb2huIFdpbGV5ICYgU29ucywgSW5jMRkwFwYDVQQLDBBJbnRlcm5ldCBI
b3N0aW5nMSMwIQYDVQQDDBpzcC5vbmxpbmVsaWJyYXJ5LndpbGV5LmNvbTAeFw0x
NjA3MDcxMzI3NDJaFw0yNjA3MDUxMzI3NDJaMIGWMQswCQYDVQQGEwJVUzETMBEG
A1UECAwKTmV3IEplcnNleTERMA8GA1UEBwwIU29tZXJzZXQxHzAdBgNVBAoMFkpv
aG4gV2lsZXkgJiBTb25zLCBJbmMxGTAXBgNVBAsMEEludGVybmV0IEhvc3Rpbmcx
IzAhBgNVBAMMGnNwLm9ubGluZWxpYnJhcnkud2lsZXkuY29tMIIBIjANBgkqhkiG
9w0BAQEFAAOCAQ8AMIIBCgKCAQEAvy8vVrFAbdrgiTptk3En1WIaszmHV1xbQp+z
4VmOjAuqOtnmfewRi0QZ6alHwk8YY92QijRNiw0wnBxtaxQqLbq5HRVvPIQG9x7l
GSik+YCnSeQBbbR/2QNm2P1zUdjOSGJMJUKEBUYsVyJkxxpaImfIPxYPAcpnSNiq
lywzg0iIEyqtZaNDKEsDs2AZZf8GrzvKicS1pl37rGUSLXDK6rSIcmEOKwhXRMuf
cd7UoYOCd0YhasjVqwH8e5/jBaPanLMnGwrIEBOwWoujiDxUrTrLgdJvIIvVA9xE
xhWE98W3a+BzLQhak+5bXyJroTVeICH82TD+42aouVmISCXuUQIDAQABMA0GCSqG
SIb3DQEBBQUAA4IBAQCaU+AavdAueqtFVDBW13ccCxAy7QxK0bibbMq1Fkxse/2q
++AIV0k/TW8gsQ7naPUTo/mfPt9CTScAYwWDzatzjnOxuEEim6C5pAd1fJluiv+A
Fjuc6a4qM4cmEpcz/qu3v4Pjf7qV5sSGoX0VJsak4ktDnSLfpxRW42nKHup0vzzr
1d2ESaW9Q4PVgH6nYVeToTlzOkBssTDxjXFTtnBFXH54uHSQvEKd5Pv6t4TAvCnD
Xx+RyGTPuF88+P/TdbmC+haWNqEvUapipA78nHnc0jQWNU1HD38oCNdVNeT+w5dT
LKbNk7/DvmH6ZoswiFm7mJBCUGHmCbCLg4aeEwEo
</ds:X509Certificate>
		</ds:X509Data>
		</ds:KeyInfo>
		<md:EncryptionMethod Algorithm="http://www.w3.org/2001/04/xmlenc#aes128-cbc"/>
		<md:EncryptionMethod Algorithm="http://www.w3.org/2001/04/xmlenc#aes192-cbc"/>
		<md:EncryptionMethod Algorithm="http://www.w3.org/2001/04/xmlenc#aes256-cbc"/>
		<md:EncryptionMethod Algorithm="http://www.w3.org/2001/04/xmlenc#tripledes-cbc"/>
		<md:EncryptionMethod Algorithm="http://www.w3.org/2009/xmlenc11#rsa-oaep"/>
		<md:EncryptionMethod Algorithm="http://www.w3.org/2001/04/xmlenc#rsa-oaep-mgf1p"/>
	</md:KeyDescriptor>
	<md:ArtifactResolutionService Binding="urn:oasis:names:tc:SAML:2.0:bindings:SOAP" Location="https://sp.onlinelibrary.wiley.com/Shibboleth.sso/Artifact/SOAP" index="1"/>
	<md:SingleLogoutService Binding="urn:oasis:names:tc:SAML:2.0:bindings:SOAP" Location="https://sp.onlinelibrary.wiley.com/Shibboleth.sso/SLO/SOAP"/>
	<md:SingleLogoutService Binding="urn:oasis:names:tc:SAML:2.0:bindings:HTTP-Redirect" Location="https://sp.onlinelibrary.wiley.com/Shibboleth.sso/SLO/Redirect"/>
	<md:SingleLogoutService Binding="urn:oasis:names:tc:SAML:2.0:bindings:HTTP-POST" Location="https://sp.onlinelibrary.wiley.com/Shibboleth.sso/SLO/POST"/>
	<md:SingleLogoutService Binding="urn:oasis:names:tc:SAML:2.0:bindings:HTTP-Artifact" Location="https://sp.onlinelibrary.wiley.com/Shibboleth.sso/SLO/Artifact"/>
	<md:ManageNameIDService Binding="urn:oasis:names:tc:SAML:2.0:bindings:SOAP" Location="https://sp.onlinelibrary.wiley.com/Shibboleth.sso/NIM/SOAP"/>
	<md:ManageNameIDService Binding="urn:oasis:names:tc:SAML:2.0:bindings:HTTP-Redirect" Location="https://sp.onlinelibrary.wiley.com/Shibboleth.sso/NIM/Redirect"/>
	<md:ManageNameIDService Binding="urn:oasis:names:tc:SAML:2.0:bindings:HTTP-POST" Location="https://sp.onlinelibrary.wiley.com/Shibboleth.sso/NIM/POST"/>
	<md:ManageNameIDService Binding="urn:oasis:names:tc:SAML:2.0:bindings:HTTP-Artifact" Location="https://sp.onlinelibrary.wiley.com/Shibboleth.sso/NIM/Artifact"/>
	<md:AssertionConsumerService Binding="urn:oasis:names:tc:SAML:2.0:bindings:HTTP-POST" Location="https://sp.onlinelibrary.wiley.com/Shibboleth.sso/SAML2/POST" index="1"/>
	<md:AssertionConsumerService Binding="urn:oasis:names:tc:SAML:2.0:bindings:HTTP-POST-SimpleSign" Location="https://sp.onlinelibrary.wiley.com/Shibboleth.sso/SAML2/POST-SimpleSign" index="2"/>
	<md:AssertionConsumerService Binding="urn:oasis:names:tc:SAML:2.0:bindings:HTTP-Artifact" Location="https://sp.onlinelibrary.wiley.com/Shibboleth.sso/SAML2/Artifact" index="3"/>
	<md:AssertionConsumerService Binding="urn:oasis:names:tc:SAML:2.0:bindings:PAOS" Location="https://sp.onlinelibrary.wiley.com/Shibboleth.sso/SAML2/ECP" index="4"/>
	<md:AssertionConsumerService Binding="urn:oasis:names:tc:SAML:1.0:profiles:browser-post" Location="https://sp.onlinelibrary.wiley.com/Shibboleth.sso/SAML/POST" index="5"/>
	<md:AssertionConsumerService Binding="urn:oasis:names:tc:SAML:1.0:profiles:artifact-01" Location="https://sp.onlinelibrary.wiley.com/Shibboleth.sso/SAML/Artifact" index="6"/>
	<md:AttributeConsumingService index="1">
		<md:ServiceName xml:lang="en">John Wiley &amp; Sons Limited: Wiley Online Library</md:ServiceName>
		<md:ServiceDescription xml:lang="en">
				This service allows Wiley Online Library users to use login credentials at their home organisations.
			</md:ServiceDescription>
		<md:RequestedAttribute FriendlyName="eduPersonScopedAffiliation" Name="urn:mace:dir:attribute-def:eduPersonScopedAffiliation" NameFormat="urn:mace:shibboleth:1.0:attributeNamespace:uri"/>
		<md:RequestedAttribute FriendlyName="eduPersonScopedAffiliation" Name="urn:oid:1.3.6.1.4.1.5923.1.1.1.9" NameFormat="urn:oasis:names:tc:SAML:2.0:attrname-format:uri"/>
	</md:AttributeConsumingService>
	</md:SPSSODescriptor>
	<md:Organization>
	<md:OrganizationName xml:lang="en">John Wiley &amp; Sons Limited</md:OrganizationName>
	<md:OrganizationDisplayName xml:lang="en">John Wiley &amp; Sons Limited: Wiley Online Library</md:OrganizationDisplayName>
	<md:OrganizationURL xml:lang="en">http://wiley.com/</md:OrganizationURL>
	</md:Organization>
	<md:ContactPerson contactType="support">
	<md:GivenName>Support</md:GivenName>
	<md:EmailAddress>mailto:wps-olhelp@wiley.com</md:EmailAddress>
	</md:ContactPerson>
	<md:ContactPerson contactType="technical">
	<md:GivenName>Support</md:GivenName>
	<md:EmailAddress>mailto:wps-olhelp@wiley.com</md:EmailAddress>
	</md:ContactPerson>
</md:EntityDescriptor>

