<?xml version='1.0' encoding='UTF-8'?>
<md:EntityDescriptor xmlns:md="urn:oasis:names:tc:SAML:2.0:metadata" xmlns:alg="urn:oasis:names:tc:SAML:metadata:algsupport" xmlns:ds="http://www.w3.org/2000/09/xmldsig#" xmlns:eidas="http://eidas.europa.eu/saml-extensions" xmlns:idpdisc="urn:oasis:names:tc:SAML:profiles:SSO:idp-discovery-protocol" xmlns:init="urn:oasis:names:tc:SAML:profiles:SSO:request-init" xmlns:mdattr="urn:oasis:names:tc:SAML:metadata:attribute" xmlns:mdrpi="urn:oasis:names:tc:SAML:metadata:rpi" xmlns:mdui="urn:oasis:names:tc:SAML:metadata:ui" xmlns:pyff="http://pyff.io/NS" xmlns:saml="urn:oasis:names:tc:SAML:2.0:assertion" xmlns:ser="http://eidas.europa.eu/metadata/servicelist" xmlns:shibmd="urn:mace:shibboleth:metadata:1.0" xmlns:xenc="http://www.w3.org/2001/04/xmlenc#" xmlns:xrd="http://docs.oasis-open.org/ns/xri/xrd-1.0" xmlns:xs="http://www.w3.org/2001/XMLSchema" xmlns:xsi="http://www.w3.org/2001/XMLSchema-instance" xmlns="urn:oasis:names:tc:SAML:2.0:metadata" entityID="https://secure.nature.com/shibboleth">
	<md:Extensions>
	<mdrpi:RegistrationInfo registrationAuthority="http://ukfederation.org.uk"/>
	</md:Extensions>
	<md:SPSSODescriptor protocolSupportEnumeration="urn:oasis:names:tc:SAML:2.0:protocol">
	<md:Extensions>
		<mdui:UIInfo>
		<mdui:DisplayName xml:lang="en">Nature Publishing Group journals</mdui:DisplayName>
		<mdui:Description xml:lang="en">Online access to Nature Publishing Group journals</mdui:Description>
		<mdui:Logo height="165" width="250">https://secure.nature.com/images/naturegroup_logo2png.PNG</mdui:Logo>
		<mdui:Logo height="70" width="220">https://secure.nature.com/images/naturegroup_logopng.PNG</mdui:Logo>
		<mdui:Logo height="165" width="250">https://secure.nature.com/images/naturegroup_logo2.GIF</mdui:Logo>
		<mdui:Logo height="70" width="220">https://secure.nature.com/images/naturegroup_logo.GIF</mdui:Logo>
		</mdui:UIInfo>
	</md:Extensions>
	<md:KeyDescriptor>
		<ds:KeyInfo>
		<ds:X509Data>
			<ds:X509Certificate>
MIIDVzCCAj+gAwIBAgIESsDsijANBgkqhkiG9w0BAQsFADBcMQswCQYDVQQGEwJV
SzEPMA0GA1UEBxMGTG9uZG9uMRIwEAYDVQQKEwlNYWNtaWxsYW4xDDAKBgNVBAsT
A05QRzEaMBgGA1UEAxMRc2VjdXJlLm5hdHVyZS5jb20wHhcNMTUwNjIzMDgxODQ3
WhcNMjUwNjIwMDgxODQ3WjBcMQswCQYDVQQGEwJVSzEPMA0GA1UEBxMGTG9uZG9u
MRIwEAYDVQQKEwlNYWNtaWxsYW4xDDAKBgNVBAsTA05QRzEaMBgGA1UEAxMRc2Vj
dXJlLm5hdHVyZS5jb20wggEiMA0GCSqGSIb3DQEBAQUAA4IBDwAwggEKAoIBAQC0
tKViXqJ6zxZ0W6kBxCk/6Jd8dqcfeODSonisCrGqAOO6uP2G81LICj/WQCSGu7J8
gY2o1ZbVKWxyXWzYUgs8ZR0zoPUVOCpo8JPjXqZFlo2mCy5Ex9H7VrUu2KqM0eGZ
8c80r7rUj0a7Yp8HvZexkt1HMcnvUYPER8XGGFqRaut7Ny/D1HlSZdQhkXVmHhyS
EkaObGDLR9ZG0EJFqjuRwk7RZu9fDuFwuo2+GVOQsR0A/dUzo49F/RDyRmjGpSpa
jirCm5paLCfb2K2mNSboNQ8VQqH5nYpxL9xuwAyt5ectvKlsun+gRJiRmw3Nbm4D
+jrVMzz/OLqCVIWVK6PRAgMBAAGjITAfMB0GA1UdDgQWBBRAYRF+J0FzkBZcXfNN
K2IXcL66ijANBgkqhkiG9w0BAQsFAAOCAQEAlQszJFL/eicmXBGXIBtz0xWpLRc4
hjvtLAD16bPmMqOXk8RYlFy3BFC9ZLs/imkOK4ixfgMNfCyddbT+//ABNTuM4a6q
eL/5oNNPJZJmqInm8QqN0fxNfSnFtyVCfX68mYBD7Onl9TcnRKKqJ4dm6C4qXQqV
AUbC7gYTTljCHXoqbLjwnY5pPFqF3CuGxi7rhyP39Dax4UKiQm3V9AZkcxq8fDs+
GsTLUceGOYa0g4LoDsUMcPo26IP8N4gcz7VHslwvmxxchptFQSwuunaMQuJhSrR1
8v8AFekwNd6YEDzxQSqKOo/9eLoymeztcHBVP9f+l39z/rvGsWlZ5C+nbg==
</ds:X509Certificate>
		</ds:X509Data>
		</ds:KeyInfo>
	</md:KeyDescriptor>
	<md:AssertionConsumerService Binding="urn:oasis:names:tc:SAML:2.0:bindings:HTTP-POST" Location="https://secure.nature.com/oa/auth/rcv/saml2/post" index="0" isDefault="true"/>
	</md:SPSSODescriptor>
	<md:Organization>
	<md:OrganizationName xml:lang="en">Springer Nature Limited</md:OrganizationName>
	<md:OrganizationDisplayName xml:lang="en">Nature Publishing Group</md:OrganizationDisplayName>
	<md:OrganizationURL xml:lang="en">http://www.nature.com/npg_/company_info/index.html</md:OrganizationURL>
	</md:Organization>
	<md:ContactPerson contactType="support">
	<md:GivenName>Springer Nature Support</md:GivenName>
	<md:EmailAddress>mailto:onlineservice@springer.com</md:EmailAddress>
	</md:ContactPerson>
	<md:ContactPerson contactType="technical">
	<md:GivenName>Platform Support</md:GivenName>
	<md:EmailAddress>mailto:platformsupport@macmillan.com</md:EmailAddress>
	</md:ContactPerson>
</md:EntityDescriptor>

