<?xml version='1.0' encoding='UTF-8'?>
<md:EntityDescriptor xmlns:md="urn:oasis:names:tc:SAML:2.0:metadata" xmlns:alg="urn:oasis:names:tc:SAML:metadata:algsupport" xmlns:ds="http://www.w3.org/2000/09/xmldsig#" xmlns:eidas="http://eidas.europa.eu/saml-extensions" xmlns:idpdisc="urn:oasis:names:tc:SAML:profiles:SSO:idp-discovery-protocol" xmlns:init="urn:oasis:names:tc:SAML:profiles:SSO:request-init" xmlns:mdattr="urn:oasis:names:tc:SAML:metadata:attribute" xmlns:mdrpi="urn:oasis:names:tc:SAML:metadata:rpi" xmlns:mdui="urn:oasis:names:tc:SAML:metadata:ui" xmlns:pyff="http://pyff.io/NS" xmlns:saml="urn:oasis:names:tc:SAML:2.0:assertion" xmlns:ser="http://eidas.europa.eu/metadata/servicelist" xmlns:shibmd="urn:mace:shibboleth:metadata:1.0" xmlns:xenc="http://www.w3.org/2001/04/xmlenc#" xmlns:xrd="http://docs.oasis-open.org/ns/xri/xrd-1.0" xmlns:xs="http://www.w3.org/2001/XMLSchema" xmlns:xsi="http://www.w3.org/2001/XMLSchema-instance" xmlns="urn:oasis:names:tc:SAML:2.0:metadata" entityID="https://gw-astronomy.org/wiki/shibboleth-sp">
	<md:Extensions>
	<mdrpi:RegistrationInfo registrationAuthority="https://incommon.org"/>
	<mdattr:EntityAttributes>
		<saml:Attribute Name="http://macedir.org/entity-category" NameFormat="urn:oasis:names:tc:SAML:2.0:attrname-format:uri">
		<saml:AttributeValue>http://refeds.org/category/research-and-scholarship</saml:AttributeValue>
		<saml:AttributeValue>http://id.incommon.org/category/registered-by-incommon</saml:AttributeValue>
		</saml:Attribute>
	</mdattr:EntityAttributes>
	</md:Extensions>
	<md:SPSSODescriptor protocolSupportEnumeration="urn:oasis:names:tc:SAML:2.0:protocol">
	<md:Extensions>
		<idpdisc:DiscoveryResponse Binding="urn:oasis:names:tc:SAML:profiles:SSO:idp-discovery-protocol" Location="https://gw-astronomy.org/wiki/Shibboleth.sso/Login" index="1"/>
		<mdui:UIInfo>
		<mdui:DisplayName xml:lang="en">Gravitational Wave Astronomy Community Wiki</mdui:DisplayName>
		<mdui:Description xml:lang="en">Gravitational Wave Astronomy Community wiki used to support collaboration across astronomy and astrophysics projects.</mdui:Description>
		<mdui:InformationURL xml:lang="en">https://gw-astronomy.org/wiki/Main/SPInfo</mdui:InformationURL>
		<mdui:PrivacyStatementURL xml:lang="en">https://wiki.gw-astronomy.org/Main/SPPrivacy</mdui:PrivacyStatementURL>
		<mdui:Logo height="60" width="80" xml:lang="en">https://gw-astronomy.org/img/gw-astro-logo.png</mdui:Logo>
		</mdui:UIInfo>
	</md:Extensions>
	<md:KeyDescriptor>
		<ds:KeyInfo>
		<ds:X509Data>
			<ds:X509Certificate>
MIIEWDCCA0CgAwIBAgIBPjANBgkqhkiG9w0BAQUFADCBhzETMBEGCgmSJomT8ixk
ARkWA29yZzEUMBIGCgmSJomT8ixkARkWBGxpZ28xDTALBgNVBAoTBExJR08xIDAe
BgNVBAsTF0NlcnRpZmljYXRlIEF1dGhvcml0aWVzMRUwEwYDVQQLEwxXZWIgU2Vy
dmljZXMxEjAQBgNVBAMTCUxJR08gQ0EgMTAeFw0xMTA0MjkxNzI0MTJaFw0yMTA0
MjgxNzI0MTJaMGoxEzARBgoJkiaJk/IsZAEZFgNvcmcxFDASBgoJkiaJk/IsZAEZ
FgRsaWdvMQ0wCwYDVQQKEwRMSUdPMRUwEwYDVQQLEwxXZWIgU2VydmljZXMxFzAV
BgNVBAMTDmd1ZXN0LmxpZ28ub3JnMIIBIjANBgkqhkiG9w0BAQEFAAOCAQ8AMIIB
CgKCAQEApxrDaMIRCnagFhhjD4rY47JBOHKjA4IS6EG1MvqG6kMXm73ZdYRhRraQ
onVmFMUPPlkR5zTlok+qvb+Iy58s6PqguQe0Tz3eEnfRlVqLaXniKNGxkef5pXFY
hndYXzkfeoclycdYZGwu12ANoG5wjADhYcWEuiyJKprfWXF/msa65rkczuMd5WFw
lde6hnpZTXa6FaeYb1Hi8Me36pHFCU3DfhARdup7DQ4t3QDEttQY1mn/pnY6vd2o
oa/jmL1iHkJbTDT6+EWhk/3XdrC1tfo1VKQ+B4RebTyzRY8Wsgn3CAyAz9K5nA7w
aYBOYhK26Z6envlE+vXviDI89J/C7QIDAQABo4HqMIHnMAwGA1UdEwEB/wQCMAAw
DgYDVR0PAQH/BAQDAgSwMB0GA1UdJQQWMBQGCCsGAQUFBwMBBggrBgEFBQcDAjAZ
BgNVHSAEEjAQMA4GDCsGAQQBgfpGAgECATA5BgNVHR8EMjAwMC6gLKAqhihodHRw
Oi8vY2EubGlnby5vcmcvNTQxNDA0YzMvNTQxNDA0YzMuY3JsMB8GA1UdIwQYMBaA
FFJu3Xuqb4VcCCLTl5+tfyNWHmrRMDEGA1UdEQQqMCiCDmd1ZXN0LmxpZ28ub3Jn
gRZzY290dC5rb3JhbmRhQGxpZ28ub3JnMA0GCSqGSIb3DQEBBQUAA4IBAQBXTyxj
WEiIQ4kG8I9ujY9AssDMi63g9m4AT7uAm6mbNJVRaYkYVy7lnRi227fBjIXr8rku
gfUhzwRULi9OUuY5eO713iB/urMn3mysch9R6heciYGzccnn5nN3gWrUN3kZ0AWd
XaIE5G8rZOACTDp7SCVyNH1eZNkk6apK9LJgblo44XppU8gZk1OIzBzeknCuZhGz
6Lnu58KItVKI+8w7FepUsXIdF6pHRLevhzW7d61QZ5iW8o2qW0TG24RDY4JJE45m
y6qIv7HErgRcZZrxupRI6NfHLBxJx22n8rBD7gmVoCLXkAftIKQZ8pBKF4c74ErF
xWUYS9G3JfMMW9UY
</ds:X509Certificate>
		</ds:X509Data>
		</ds:KeyInfo>
	</md:KeyDescriptor>
	<md:AssertionConsumerService Binding="urn:oasis:names:tc:SAML:2.0:bindings:HTTP-POST" Location="https://gw-astronomy.org/wiki/Shibboleth.sso/SAML2/POST" index="1"/>
	<md:AssertionConsumerService Binding="urn:oasis:names:tc:SAML:2.0:bindings:HTTP-Artifact" Location="https://gw-astronomy.org/wiki/Shibboleth.sso/SAML2/Artifact" index="2"/>
	<md:AssertionConsumerService Binding="urn:oasis:names:tc:SAML:2.0:bindings:PAOS" Location="https://gw-astronomy.org/wiki/Shibboleth.sso/SAML2/ECP" index="3"/>
	<md:AssertionConsumerService Binding="urn:oasis:names:tc:SAML:2.0:bindings:HTTP-POST" Location="https://wiki.gw-astronomy.org/Shibboleth.sso/SAML2/POST" index="4"/>
	<md:AssertionConsumerService Binding="urn:oasis:names:tc:SAML:2.0:bindings:HTTP-Artifact" Location="https://wiki.gw-astronomy.org/Shibboleth.sso/SAML2/Artifact" index="5"/>
	<md:AssertionConsumerService Binding="urn:oasis:names:tc:SAML:2.0:bindings:PAOS" Location="https://wiki.gw-astronomy.org/Shibboleth.sso/SAML2/ECP" index="6"/>
	<md:AttributeConsumingService index="1">
		<md:ServiceName xml:lang="en">Gravitational Wave Astronomy Community Wiki</md:ServiceName>
		<md:ServiceDescription xml:lang="en">Gravitational Wave Astronomy Community wiki used to support collaboration across astronomy and astrophysics projects.</md:ServiceDescription>
		<md:RequestedAttribute FriendlyName="eduPersonPrincipalName" Name="urn:oid:1.3.6.1.4.1.5923.1.1.1.6" NameFormat="urn:oasis:names:tc:SAML:2.0:attrname-format:uri" isRequired="true"/>
	</md:AttributeConsumingService>
	</md:SPSSODescriptor>
	<md:Organization>
	<md:OrganizationName xml:lang="en">University of Wisconsin-Milwaukee</md:OrganizationName>
	<md:OrganizationDisplayName xml:lang="en">University of Wisconsin-Milwaukee</md:OrganizationDisplayName>
	<md:OrganizationURL xml:lang="en">http://www.uwm.edu/</md:OrganizationURL>
	</md:Organization>
	<md:ContactPerson contactType="support">
	<md:GivenName>UWM CGCA Help</md:GivenName>
	<md:EmailAddress>uwm-help@gravity.phys.uwm.edu</md:EmailAddress>
	</md:ContactPerson>
	<md:ContactPerson contactType="administrative">
	<md:GivenName>Warren Anderson</md:GivenName>
	<md:EmailAddress>anders15@uwm.edu</md:EmailAddress>
	</md:ContactPerson>
	<md:ContactPerson xmlns:remd="http://refeds.org/metadata" contactType="other" remd:contactType="http://refeds.org/metadata/contactType/security">
	<md:GivenName>LIGO Scientific Collaboration Security Committee</md:GivenName>
	<md:EmailAddress>lsc-seccomm@ligo.org</md:EmailAddress>
	</md:ContactPerson>
	<md:ContactPerson contactType="technical">
	<md:GivenName>Michael Manske</md:GivenName>
	<md:EmailAddress>manskema@uwm.edu</md:EmailAddress>
	</md:ContactPerson>
</md:EntityDescriptor>

