<?xml version='1.0' encoding='UTF-8'?>
<md:EntityDescriptor xmlns:md="urn:oasis:names:tc:SAML:2.0:metadata" xmlns:alg="urn:oasis:names:tc:SAML:metadata:algsupport" xmlns:ds="http://www.w3.org/2000/09/xmldsig#" xmlns:eidas="http://eidas.europa.eu/saml-extensions" xmlns:idpdisc="urn:oasis:names:tc:SAML:profiles:SSO:idp-discovery-protocol" xmlns:init="urn:oasis:names:tc:SAML:profiles:SSO:request-init" xmlns:mdattr="urn:oasis:names:tc:SAML:metadata:attribute" xmlns:mdrpi="urn:oasis:names:tc:SAML:metadata:rpi" xmlns:mdui="urn:oasis:names:tc:SAML:metadata:ui" xmlns:pyff="http://pyff.io/NS" xmlns:saml="urn:oasis:names:tc:SAML:2.0:assertion" xmlns:ser="http://eidas.europa.eu/metadata/servicelist" xmlns:shibmd="urn:mace:shibboleth:metadata:1.0" xmlns:xenc="http://www.w3.org/2001/04/xmlenc#" xmlns:xrd="http://docs.oasis-open.org/ns/xri/xrd-1.0" xmlns:xs="http://www.w3.org/2001/XMLSchema" xmlns:xsi="http://www.w3.org/2001/XMLSchema-instance" xmlns="urn:oasis:names:tc:SAML:2.0:metadata" entityID="https://idp-lab.martinique.univ-antilles.fr/idp/shibboleth">
	<md:Extensions>
	<mdrpi:RegistrationInfo registrationAuthority="https://federation.renater.fr/" registrationInstant="2019-06-04T23:03:57Z">
		<mdrpi:RegistrationPolicy xml:lang="en">https://services.renater.fr/federation/en/metadata_registration_practice_statement</mdrpi:RegistrationPolicy>
	</mdrpi:RegistrationInfo>
	<mdattr:EntityAttributes>
		<saml:Attribute Name="urn:oasis:names:tc:SAML:attribute:assurance-certification" NameFormat="urn:oasis:names:tc:SAML:2.0:attrname-format:uri">
		<saml:AttributeValue>https://refeds.org/sirtfi</saml:AttributeValue>
		</saml:Attribute>
	</mdattr:EntityAttributes>
	</md:Extensions>
	<md:IDPSSODescriptor protocolSupportEnumeration="urn:oasis:names:tc:SAML:1.1:protocol urn:mace:shibboleth:1.0 urn:oasis:names:tc:SAML:2.0:protocol">
	<md:Extensions>
		<shibmd:Scope regexp="false">univ-antilles.fr</shibmd:Scope>
		<mdui:UIInfo>
		<mdui:DisplayName xml:lang="en">Idp-lab.martinique.univ-antilles.fr</mdui:DisplayName>
		<mdui:InformationURL xml:lang="fr">http://www.univ-antilles.fr</mdui:InformationURL>
		<mdui:Description xml:lang="en">Idp Laboratoire</mdui:Description>
		<mdui:DisplayName xml:lang="fr">Idp-lab.martinique.univ-antilles.fr</mdui:DisplayName>
		<mdui:Description xml:lang="fr">Idp Laboratoire</mdui:Description>
		</mdui:UIInfo>
	</md:Extensions>
	<md:KeyDescriptor use="signing">
		<ds:KeyInfo>
		<ds:X509Data>
			<ds:X509Certificate>
MIIEfTCCAuWgAwIBAgIUH3qQ3DEr4vsoZP6KRgoC+c+C6howDQYJKoZIhvcNAQEL
BQAwLzEtMCsGA1UEAwwkaWRwLWxhYi5tYXJ0aW5pcXVlLnVuaXYtYW50aWxsZXMu
ZnIvMB4XDTE5MDYwNDIwMDkzMFoXDTM5MDYwNDIwMDkzMFowLzEtMCsGA1UEAwwk
aWRwLWxhYi5tYXJ0aW5pcXVlLnVuaXYtYW50aWxsZXMuZnIvMIIBojANBgkqhkiG
9w0BAQEFAAOCAY8AMIIBigKCAYEA1OKgik01pQrGV9rXGUI9t8Lni4sYWurGGU7e
gg8wyG94osc/hdPx6lPRdo8DgrS7Mx/2nWd2xaChRUW2ewRRIIq7cUpgmbIFIa99
KgQADpHJ59hTuDvcWH2F8abMm6q2Vtg/8AH+7bFgA26j1SdJo3VThl0tkTqzJIVm
gPA7iywWDicbkqlsWR5TEEvKitsErZWmWgIgM8xRt1NLwQS5O4cGfDYmyds5rj1O
4+YKZGIwv7lIlUIp5FGqbZVJtTqkkB0gXbNlGP+TivuTVlfzbH2ivBHnXY7psyHH
5XU/pz3uqCcAW414MlW5ltKaUeXbD9oULs20S/MAfpy2KbyV0oDRChz1NRRQ62X4
Am+r26rny2hBTbWIPgfONPr0LB8qKU6V053oMTV1NkELE0cKF+g+ekthY9dobEMF
WLDjVedWb7eVYfggBKwKK7PDDmBfg6oUnVdJa+xZshGLoDxhG5tcwlq8iFobD6SI
KXzKYEw0Ndkcg8tx35pJFm5yprYtAgMBAAGjgZAwgY0wHQYDVR0OBBYEFCHkNp/u
Co9hzfVwyZXvKeuyCwEjMGwGA1UdEQRlMGOCJGlkcC1sYWIubWFydGluaXF1ZS51
bml2LWFudGlsbGVzLmZyL4Y7aHR0cHM6Ly9pZHAtbGFiLm1hcnRpbmlxdWUudW5p
di1hbnRpbGxlcy5mci8vaWRwL3NoaWJib2xldGgwDQYJKoZIhvcNAQELBQADggGB
AEA3GIYnktthYR2o+rlIKFavX7LZ9q9daD9i4GF1+66ize/ClvvUYHPKvpIK1v5k
qfGcMy7nxvkL6t/59RCfnYNnXGTK8Q7dFFEzlmYT72PlaVBd2gisFX9ptNvGOaVP
uD+/ZPwCaLRs+/yt6rAlNZ+cA+lhy3dhweYpKhygc1rdqsXtVAmrFn/DIi/AQYa0
n1I0vujxNW9yepCXJIi8ZZPkmAuIpmLqUTAKoWliPZkDaEjE3x0LhD/xrr6OsFvg
ZS8D1czHq6xTs5wAAcdXrahk0EWncDBBN+NBmqjpmiDcfZZ53o8LDQu1spwA51W1
Tk+l4qgwqaUnrtr7TRR1qZSkTG5SGYbVVGDne3sEWUuuUC2C9xPtWdj5BJE9wrKn
zZ6F5TErpbp3cabh6KJXGuilda2XNmSOB1yJ4uPbWUirMAbNdH4GHipfF7N/EA9q
4UjuC1/1woBKdgZkjzRPRx2x2sQUi2uxVWNdi2gPCStT+I1cqE6OAlvme1r94J6z
Pw==
</ds:X509Certificate>
		</ds:X509Data>
		</ds:KeyInfo>
	</md:KeyDescriptor>
	<md:NameIDFormat>urn:mace:shibboleth:1.0:nameIdentifier</md:NameIDFormat>
	<md:NameIDFormat>urn:oasis:names:tc:SAML:2.0:nameid-format:transient</md:NameIDFormat>
	<md:SingleSignOnService Binding="urn:oasis:names:tc:SAML:2.0:bindings:HTTP-POST" Location="https://idp-lab.martinique.univ-antilles.fr/idp/profile/SAML2/POST/SSO"/>
	<md:SingleSignOnService Binding="urn:oasis:names:tc:SAML:2.0:bindings:HTTP-Redirect" Location="https://idp-lab.martinique.univ-antilles.fr/idp/profile/SAML2/Redirect/SSO"/>
	<md:SingleSignOnService Binding="urn:mace:shibboleth:1.0:profiles:AuthnRequest" Location="https://idp-lab.martinique.univ-antilles.fr/idp/profile/Shibboleth/SSO"/>
	</md:IDPSSODescriptor>
	<md:Organization>
	<md:OrganizationName xml:lang="en">Université des Antilles</md:OrganizationName>
	<md:OrganizationDisplayName xml:lang="en">Université des Antilles</md:OrganizationDisplayName>
	<md:OrganizationURL xml:lang="en">http://www.univ-antilles.fr</md:OrganizationURL>
	</md:Organization>
	<md:ContactPerson contactType="technical">
	<md:SurName>Robert Bolin</md:SurName>
	<md:EmailAddress>mailto:robert.bolin@univ-antilles.fr</md:EmailAddress>
	</md:ContactPerson>
	<md:ContactPerson xmlns:remd="http://refeds.org/metadata" contactType="other" remd:contactType="http://refeds.org/metadata/contactType/security">
	<md:GivenName>Renater-Equipe Federation</md:GivenName>
	<md:EmailAddress>mailto:fed-sirtfi@support.renater.fr</md:EmailAddress>
	</md:ContactPerson>
</md:EntityDescriptor>

