<?xml version='1.0' encoding='UTF-8'?>
<md:EntityDescriptor xmlns:md="urn:oasis:names:tc:SAML:2.0:metadata" xmlns:alg="urn:oasis:names:tc:SAML:metadata:algsupport" xmlns:ds="http://www.w3.org/2000/09/xmldsig#" xmlns:eidas="http://eidas.europa.eu/saml-extensions" xmlns:idpdisc="urn:oasis:names:tc:SAML:profiles:SSO:idp-discovery-protocol" xmlns:init="urn:oasis:names:tc:SAML:profiles:SSO:request-init" xmlns:mdattr="urn:oasis:names:tc:SAML:metadata:attribute" xmlns:mdrpi="urn:oasis:names:tc:SAML:metadata:rpi" xmlns:mdui="urn:oasis:names:tc:SAML:metadata:ui" xmlns:pyff="http://pyff.io/NS" xmlns:saml="urn:oasis:names:tc:SAML:2.0:assertion" xmlns:ser="http://eidas.europa.eu/metadata/servicelist" xmlns:shibmd="urn:mace:shibboleth:metadata:1.0" xmlns:xenc="http://www.w3.org/2001/04/xmlenc#" xmlns:xrd="http://docs.oasis-open.org/ns/xri/xrd-1.0" xmlns:xs="http://www.w3.org/2001/XMLSchema" xmlns:xsi="http://www.w3.org/2001/XMLSchema-instance" xmlns="urn:oasis:names:tc:SAML:2.0:metadata" entityID="https://sp.silverchair.com/allen/staging/shibboleth">
	<md:Extensions>
	<mdrpi:RegistrationInfo registrationAuthority="https://incommon.org"/>
	<mdattr:EntityAttributes>
		<saml:Attribute Name="http://macedir.org/entity-category" NameFormat="urn:oasis:names:tc:SAML:2.0:attrname-format:uri">
		<saml:AttributeValue>http://id.incommon.org/category/registered-by-incommon</saml:AttributeValue>
		</saml:Attribute>
	</mdattr:EntityAttributes>
	</md:Extensions>
	<md:SPSSODescriptor protocolSupportEnumeration="urn:oasis:names:tc:SAML:1.1:protocol urn:oasis:names:tc:SAML:2.0:protocol">
	<md:Extensions>
		<mdui:UIInfo>
		<mdui:DisplayName xml:lang="en">Silverchair Staging: Allen Press</mdui:DisplayName>
		<mdui:PrivacyStatementURL xml:lang="en">https://www.silverchair.com/privacy/</mdui:PrivacyStatementURL>
		<mdui:Logo height="31" width="200" xml:lang="en">https://11eahk451t3g2es8u53czolt39w-wpengine.netdna-ssl.com/wp-content/uploads/2017/09/platform-tools-1.png</mdui:Logo>
		</mdui:UIInfo>
	</md:Extensions>
	<md:KeyDescriptor>
		<ds:KeyInfo>
		<ds:X509Data>
			<ds:X509Certificate>
MIIDBjCCAe6gAwIBAgIJAMdLIPzHYlKyMA0GCSqGSIb3DQEBBQUAMCAxHjAcBgNV
BAMTFXNjbS1zdGFnd2ViMDEuc2lzLmxhbjAeFw0xOTA3MzExODQ4MjhaFw0yOTA3
MjgxODQ4MjhaMCAxHjAcBgNVBAMTFXNjbS1zdGFnd2ViMDEuc2lzLmxhbjCCASIw
DQYJKoZIhvcNAQEBBQADggEPADCCAQoCggEBAM8RzhVrRZhOQ0nyPr8tQCu4KaJH
dRVNT2TH6BmecJq7VdlvXdP8Y00be/U/L0LdWlSJde9dVd9zYnVQqqHh1jmkPrTf
EsMDBgzQfcnqqV2wUp3SeMbMVd59tVTc+07O2XIYREXhAZOrd3Q8xtkyKqFHEIRK
cqyZEJjUe+feHZazUJNtv+0pVUK/8Wt8KWyPg8aYploDN5CIss3V+Oji/n672Gaz
kPU1Ds+5Ajy1Y5Oa/gtUQdxs4uqBUShVcIG45tfcLXlRF4QwqFWmxMdDA8My5Jp8
cs3VLAX9C+f4ySkoKGxc/mhwCyL4Xu9pb1OPgPof7M+WAKpWwPSKIVDDzRcCAwEA
AaNDMEEwIAYDVR0RBBkwF4IVc2NtLXN0YWd3ZWIwMS5zaXMubGFuMB0GA1UdDgQW
BBQSIwMzvnPS4MwvbsJAmj6iL1VE+DANBgkqhkiG9w0BAQUFAAOCAQEAkayVY991
4BpwfNBC/Pnuu1hN5xPW9SM0mD1Y7YqT+xrw8YAk+qGUpOE68iP9C89m4pSyRjmF
41NWRtDUQmaxgL0Xwnp1FMpGIre+tNFCq+hjN57pr3aFejWGSw+TerRbAM81ffGI
cr0Tij5qktIcYCrM4q7PuR+nGC5ddfEyfzSmHhWNOOpNupC84MUYRBXMG9bT2SPV
1NMMUO347LlQxVuMqCkZx9Yj/zb7PbVxTVd8lvnZWfaTXYV68DLwPBDWreX5bZjx
3J6W5ilJp2J4GT/LS4W1zqC4UWkeynFdklwRrsteQQcX04WHorJ2nzaqDm/P9ffN
+qCd56s4vb5tjw==
</ds:X509Certificate>
		</ds:X509Data>
		</ds:KeyInfo>
	</md:KeyDescriptor>
	<md:SingleLogoutService Binding="urn:oasis:names:tc:SAML:2.0:bindings:HTTP-POST" Location="https://allenrc.silverchair.com/Shibboleth.sso/SLO/POST"/>
	<md:SingleLogoutService Binding="urn:oasis:names:tc:SAML:2.0:bindings:HTTP-Redirect" Location="https://allenrc.silverchair.com/Shibboleth.sso/SLO/Redirect"/>
	<md:SingleLogoutService Binding="urn:oasis:names:tc:SAML:2.0:bindings:SOAP" Location="https://allenrc.silverchair.com/Shibboleth.sso/SLO/SOAP"/>
	<md:AssertionConsumerService Binding="urn:oasis:names:tc:SAML:2.0:bindings:HTTP-POST" Location="https://allenrc.silverchair.com/Shibboleth.sso/SAML2/POST" index="1"/>
	<md:AssertionConsumerService Binding="urn:oasis:names:tc:SAML:2.0:bindings:HTTP-POST-SimpleSign" Location="https://allenrc.silverchair.com/Shibboleth.sso/SAML2/POST-SimpleSign" index="2"/>
	<md:AssertionConsumerService Binding="urn:oasis:names:tc:SAML:2.0:bindings:HTTP-Artifact" Location="https://allenrc.silverchair.com/Shibboleth.sso/SAML2/Artifact" index="3"/>
	<md:AssertionConsumerService Binding="urn:oasis:names:tc:SAML:2.0:bindings:PAOS" Location="https://allenrc.silverchair.com/Shibboleth.sso/SAML2/ECP" index="4"/>
	<md:AssertionConsumerService Binding="urn:oasis:names:tc:SAML:1.0:profiles:browser-post" Location="https://allenrc.silverchair.com/Shibboleth.sso/SAML/POST" index="5"/>
	<md:AssertionConsumerService Binding="urn:oasis:names:tc:SAML:1.0:profiles:artifact-01" Location="https://allenrc.silverchair.com/Shibboleth.sso/SAML/Artifact" index="6"/>
	</md:SPSSODescriptor>
	<md:Organization>
	<md:OrganizationName xml:lang="en">Silverchair Information Systems</md:OrganizationName>
	<md:OrganizationDisplayName xml:lang="en">Silverchair Information Systems</md:OrganizationDisplayName>
	<md:OrganizationURL xml:lang="en">https://www.silverchair.com/</md:OrganizationURL>
	</md:Organization>
	<md:ContactPerson contactType="administrative">
	<md:GivenName>Shibboleth Admin</md:GivenName>
	<md:EmailAddress>ShibbolethAdmin@silverchair.com</md:EmailAddress>
	</md:ContactPerson>
	<md:ContactPerson contactType="technical">
	<md:GivenName>Shibboleth Admin</md:GivenName>
	<md:EmailAddress>ShibbolethAdmin@silverchair.com</md:EmailAddress>
	</md:ContactPerson>
	<md:ContactPerson xmlns:remd="http://refeds.org/metadata" contactType="other" remd:contactType="http://refeds.org/metadata/contactType/security">
	<md:GivenName>Shibboleth Admin</md:GivenName>
	<md:EmailAddress>ShibbolethAdmin@silverchair.com</md:EmailAddress>
	</md:ContactPerson>
	<md:ContactPerson contactType="support">
	<md:GivenName>Shibboleth Admin</md:GivenName>
	<md:EmailAddress>ShibbolethAdmin@silverchair.com</md:EmailAddress>
	</md:ContactPerson>
</md:EntityDescriptor>

