<?xml version='1.0' encoding='UTF-8'?>
<md:EntityDescriptor xmlns:md="urn:oasis:names:tc:SAML:2.0:metadata" xmlns:alg="urn:oasis:names:tc:SAML:metadata:algsupport" xmlns:ds="http://www.w3.org/2000/09/xmldsig#" xmlns:eidas="http://eidas.europa.eu/saml-extensions" xmlns:idpdisc="urn:oasis:names:tc:SAML:profiles:SSO:idp-discovery-protocol" xmlns:init="urn:oasis:names:tc:SAML:profiles:SSO:request-init" xmlns:mdattr="urn:oasis:names:tc:SAML:metadata:attribute" xmlns:mdrpi="urn:oasis:names:tc:SAML:metadata:rpi" xmlns:mdui="urn:oasis:names:tc:SAML:metadata:ui" xmlns:pyff="http://pyff.io/NS" xmlns:saml="urn:oasis:names:tc:SAML:2.0:assertion" xmlns:ser="http://eidas.europa.eu/metadata/servicelist" xmlns:shibmd="urn:mace:shibboleth:metadata:1.0" xmlns:xenc="http://www.w3.org/2001/04/xmlenc#" xmlns:xrd="http://docs.oasis-open.org/ns/xri/xrd-1.0" xmlns:xs="http://www.w3.org/2001/XMLSchema" xmlns:xsi="http://www.w3.org/2001/XMLSchema-instance" xmlns="urn:oasis:names:tc:SAML:2.0:metadata" entityID="https://idp.ccs.ryerson.ca/idp/shibboleth">
	<md:Extensions>
	<mdrpi:RegistrationInfo registrationAuthority="http://www.canarie.ca" registrationInstant="2015-08-10T18:29:00Z">
		<mdrpi:RegistrationPolicy xml:lang="en">https://www.canarie.ca/?wpdmdl=10721</mdrpi:RegistrationPolicy>
		<mdrpi:RegistrationPolicy xml:lang="fr">https://www.canarie.ca/?wpdmdl=10723</mdrpi:RegistrationPolicy>
	</mdrpi:RegistrationInfo>
	</md:Extensions>
	<md:IDPSSODescriptor protocolSupportEnumeration="urn:oasis:names:tc:SAML:2.0:protocol urn:oasis:names:tc:SAML:1.1:protocol urn:mace:shibboleth:1.0">
	<md:Extensions>
		<shibmd:Scope regexp="false">ryerson.ca</shibmd:Scope>
		<mdui:UIInfo>
		<mdui:DisplayName xml:lang="en">Ryerson University</mdui:DisplayName>
		<mdui:Description xml:lang="en">Ryerson University</mdui:Description>
		<mdui:InformationURL xml:lang="en">http://www.ryerson.ca/</mdui:InformationURL>
		<mdui:PrivacyStatementURL xml:lang="en">http://www.ryerson.ca/privacy/</mdui:PrivacyStatementURL>
		</mdui:UIInfo>
	</md:Extensions>
	<md:KeyDescriptor>
		<ds:KeyInfo>
		<ds:X509Data>
			<ds:X509Certificate>
MIIDNDCCAhygAwIBAgIVALZUh6caWiqzKPf57FI/Rr+R0PzSMA0GCSqGSIb3DQEB
BQUAMB0xGzAZBgNVBAMMEmlkcC5jY3MucnllcnNvbi5jYTAeFw0xNTA4MDcxMzU1
MjdaFw0zNTA4MDcxMzU1MjdaMB0xGzAZBgNVBAMMEmlkcC5jY3MucnllcnNvbi5j
YTCCASIwDQYJKoZIhvcNAQEBBQADggEPADCCAQoCggEBAJI1tjYoItnu6PqfQGIs
h3q49qns/9hgFrNfOXXmOswiC+FzhXECm/cu6e20AYLBtNYdmiMH3Eo/oO9Zvpit
V1if12/EdTa3fE/wS2PZcx8urxjzHpiIPL0079TzhAAqOymGBlF45xtNx+HiP+cb
YGWMr1RErm6odkoyvLhBdWOJu27wcH2WrDWFpwqsKMeYVpRN3TIKXAD6lcyNgrym
UPqmH0Fo1d91i3TwV/WFNNGu2gcBBj5ya7pTOmnqc05bC56YaspQe6mCZGKV/Uxk
LfuK+UJNWbk+SBCv1jQ3d8EpmrkpF1kyE/kXLaOMnPYwDbtoyInkmniJwQZ/iKeq
9ecCAwEAAaNrMGkwHQYDVR0OBBYEFNflsjcICb4QcPOT658aolPVUyLtMEgGA1Ud
EQRBMD+CEmlkcC5jY3MucnllcnNvbi5jYYYpaHR0cHM6Ly9pZHAuY2NzLnJ5ZXJz
b24uY2EvaWRwL3NoaWJib2xldGgwDQYJKoZIhvcNAQEFBQADggEBABzWLsKJhSrK
gxQY4mKb47+5p3hZILFMNaqTFvsfqXeq7HKgVR2FIF3W4NMiiapNKUVkGuNWDvwX
7dls+lZLOJxFOEIfli8kZ7G1R9c9A+g9ctw/pQcH7MgPekTlEXPiWMSQ4h4af1mJ
fGjVnTPEyfMXnXlghi28R6jB/v//qdfeBxu74nKsGvgDmBK7OxAF657ZEKR/YLDq
h0b4SlLkCN+56lwc2vQx+0wudrFvcefrKRNcuH6M5W0oCO/dG+3QWkraOp8pwBtO
4dNXpUGRozP/+kCacHhScMWto60wNN1MDKMdUyvjmo+glT+cjls4BL6EXR77fDul
fKV8acgRrsY=
</ds:X509Certificate>
		</ds:X509Data>
		</ds:KeyInfo>
	</md:KeyDescriptor>
	<md:ArtifactResolutionService Binding="urn:oasis:names:tc:SAML:1.0:bindings:SOAP-binding" Location="https://idp.ccs.ryerson.ca:8443/idp/profile/SAML1/SOAP/ArtifactResolution" index="1"/>
	<md:ArtifactResolutionService Binding="urn:oasis:names:tc:SAML:2.0:bindings:SOAP" Location="https://idp.ccs.ryerson.ca:8443/idp/profile/SAML2/SOAP/ArtifactResolution" index="2"/>
	<md:SingleLogoutService Binding="urn:oasis:names:tc:SAML:2.0:bindings:HTTP-Redirect" Location="https://idp.ccs.ryerson.ca/idp/profile/SAML2/Redirect/SLO"/>
	<md:SingleLogoutService Binding="urn:oasis:names:tc:SAML:2.0:bindings:HTTP-POST" Location="https://idp.ccs.ryerson.ca/idp/profile/SAML2/POST/SLO"/>
	<md:SingleLogoutService Binding="urn:oasis:names:tc:SAML:2.0:bindings:SOAP" Location="https://idp.ccs.ryerson.ca:8443/idp/profile/SAML2/SOAP/SLO"/>
	<md:NameIDFormat>urn:mace:shibboleth:1.0:nameIdentifier</md:NameIDFormat>
	<md:NameIDFormat>urn:oasis:names:tc:SAML:2.0:nameid-format:transient</md:NameIDFormat>
	<md:SingleSignOnService Binding="urn:mace:shibboleth:1.0:profiles:AuthnRequest" Location="https://idp.ccs.ryerson.ca/idp/profile/Shibboleth/SSO"/>
	<md:SingleSignOnService Binding="urn:oasis:names:tc:SAML:2.0:bindings:HTTP-POST" Location="https://idp.ccs.ryerson.ca/idp/profile/SAML2/POST/SSO"/>
	<md:SingleSignOnService Binding="urn:oasis:names:tc:SAML:2.0:bindings:HTTP-POST-SimpleSign" Location="https://idp.ccs.ryerson.ca/idp/profile/SAML2/POST-SimpleSign/SSO"/>
	<md:SingleSignOnService Binding="urn:oasis:names:tc:SAML:2.0:bindings:HTTP-Redirect" Location="https://idp.ccs.ryerson.ca/idp/profile/SAML2/Redirect/SSO"/>
	</md:IDPSSODescriptor>
	<md:Organization>
	<md:OrganizationName xml:lang="en">Ryerson University</md:OrganizationName>
	<md:OrganizationDisplayName xml:lang="en">Ryerson University</md:OrganizationDisplayName>
	<md:OrganizationURL xml:lang="en">http://www.ryerson.ca/</md:OrganizationURL>
	</md:Organization>
	<md:ContactPerson contactType="technical">
	<md:GivenName>Alvin</md:GivenName>
	<md:SurName>Yeung</md:SurName>
	<md:EmailAddress>mailto:a4yeung@ryerson.ca</md:EmailAddress>
	</md:ContactPerson>
	<md:ContactPerson contactType="support">
	<md:GivenName>Alvin</md:GivenName>
	<md:SurName>Yeung</md:SurName>
	<md:EmailAddress>mailto:a4yeung@ryerson.ca</md:EmailAddress>
	</md:ContactPerson>
</md:EntityDescriptor>

